empire_chain/__init__.py
empire_chain/agent/agent.py
empire_chain/cool_stuff/podcast.py
empire_chain/cool_stuff/visualizer.py
empire_chain/embeddings/__init__.py
empire_chain/embeddings/openai_embeddings.py
empire_chain/embeddings/sentence_transformers_embeddings.py
empire_chain/llms/__init__.py
empire_chain/llms/llms.py
empire_chain/payments/__init__.py
empire_chain/payments/stripe.py
empire_chain/phidata/finance_agent.py
empire_chain/phidata/web_agent.py
empire_chain/playground/__init__.py
empire_chain/playground/compare_llms.py
empire_chain/prompt_templates/__init__.py
empire_chain/prompt_templates/templates.py
empire_chain/streamlit/__init__.py
empire_chain/streamlit/base_chatbot.py
empire_chain/streamlit/pdf_chatbot.py
empire_chain/stt/stt.py
empire_chain/tools/crawl4ai.py
empire_chain/tools/docling.py
empire_chain/tools/file_reader.py
empire_chain/vector_stores/__init__.py
empire_chain/vector_stores/qdrant.py
empire_chain-0.5.4.dist-info/licenses/LICENSE
empire_chain-0.5.4.dist-info/METADATA
empire_chain-0.5.4.dist-info/WHEEL
empire_chain-0.5.4.dist-info/top_level.txt
empire_chain-0.5.4.dist-info/RECORD
