Metadata-Version: 2.4
Name: empire-chain
Version: 0.5.4
Summary: An orchestration framework for all your AI needs
Home-page: https://github.com/manas95826/empire-chain
Author: Manas Chopra
Author-email: manaschopra95826@gmail.com
Requires-Python: >=3.10
License-File: LICENSE
Requires-Dist: openai
Requires-Dist: anthropic
Requires-Dist: groq
Requires-Dist: python-dotenv
Requires-Dist: qdrant-client
Requires-Dist: requests
Requires-Dist: PyPDF2
Requires-Dist: python-docx
Requires-Dist: soundfile
Dynamic: author
Dynamic: author-email
Dynamic: home-page
Dynamic: license-file
Dynamic: requires-python
